lespy/__init__.py
lespy/exceptions.py
lespy/utils.py
lespy/confs/__init__.py
lespy/confs/classes.py
lespy/confs/utils.py
lespy/converters/__init__.py
lespy/converters/base.py
lespy/converters/converters.py
lespy/core/__init__.py
lespy/core/app.py
lespy/core/base.py
lespy/core/container.py
lespy/core/router.py
lespy/http/__init__.py
lespy/http/utils.py
lespy/http/request/__init__.py
lespy/http/request/base.py
lespy/http/response/__init__.py
lespy/http/response/base.py
lespy/server/__init__.py
lespy/server/handlers.py
Lespy-0.1.2.dist-info/LICENSE
Lespy-0.1.2.dist-info/METADATA
Lespy-0.1.2.dist-info/WHEEL
Lespy-0.1.2.dist-info/top_level.txt
Lespy-0.1.2.dist-info/RECORD
